libaxion_dmx/__init__.py
libaxion_dmx/axion_dmx_api.py
libaxion_dmx-1.0.6.dist-info/LICENSE
libaxion_dmx-1.0.6.dist-info/METADATA
libaxion_dmx-1.0.6.dist-info/WHEEL
libaxion_dmx-1.0.6.dist-info/top_level.txt
libaxion_dmx-1.0.6.dist-info/RECORD
