Metadata-Version: 2.2
Name: libaxion_dmx
Version: 1.0.6
Summary: A Python API for controlling Axion Lighting DMX controllers
Author: Vrncanac
Author-email: jana13eng@gmail.com
Classifier: Programming Language :: Python :: 3
Classifier: License :: OSI Approved :: MIT License
Classifier: Operating System :: OS Independent
Requires-Python: >=3.9
Dynamic: author
Dynamic: author-email
Dynamic: classifier
Dynamic: description
Dynamic: description-content-type
Dynamic: requires-python
Dynamic: summary
